{"coordinateSystem":"x increases to the right, y increases upward, negative z travels down the alley toward the target wall.","mode":"ready","thrownBrickCap":10,"throwOrigin":[0,1.22,2.8],"camera":{"position":[0.1,3.2,3.3],"target":[0,1.4,-4.7]},"aim":null,"thrownBricks":[],"wallBricks":[{"id":"wall-0","position":[-0.61,0.11,-4.95],"velocity":[0,0,0],"sleeping":false},{"id":"wall-1","position":[0,0.11,-4.95],"velocity":[0,0,0],"sleeping":false},{"id":"wall-2","position":[0.6,0.11,-4.95],"velocity":[0,0,0],"sleeping":false},{"id":"wall-3","position":[-0.61,0.32,-4.95],"velocity":[0,0,0],"sleeping":false},{"id":"wall-4","position":[0,0.32,-4.95],"velocity":[0,0,0],"sleeping":false},{"id":"wall-5","position":[0.6,0.32,-4.95],"velocity":[0,0,0],"sleeping":false},{"id":"wall-6","position":[-0.61,0.54,-4.95],"velocity":[0,0,0],"sleeping":false},{"id":"wall-7","position":[0,0.54,-4.95],"velocity":[0,0,0],"sleeping":false},{"id":"wall-8","position":[0.6,0.54,-4.95],"velocity":[0,0,0],"sleeping":false},{"id":"wall-9","position":[-0.61,0.76,-4.95],"velocity":[0,0,0],"sleeping":false},{"id":"wall-10","position":[0,0.76,-4.95],"velocity":[0,0,0],"sleeping":false},{"id":"wall-11","position":[0.6,0.76,-4.95],"velocity":[0,0,0],"sleeping":false}],"lastImpact":null}